Workbook

Sheet Notes & Tie-Out
A1: Iowa City Community School District
A2: Balance Sheet — Governmental Funds — by Fund, FY2015–FY2025
A4: Overview
A5: One worksheet per governmental fund. Rows follow the audited ACFR "Balance Sheet – Governmental Funds" line structure.
A6: Columns are fiscal years ended June 30, 2015 through 2025. All figures in US dollars.
A7: Subtotals (Total assets, Total liabilities, Total deferred inflows, Total fund balances) are live SUM formulas.
A8: Each tab ends with a Balance check row = Total assets − (Liabilities + Deferred inflows + Fund balances); it should equal "-" (zero).
A10: Sources
A11: FY2015–FY2024: Iowa City CSD audited Annual Comprehensive Financial Reports (Balance Sheet – Governmental Funds).
A12: FY2025: District "FY25 balance sheet by fund" CSV, mapped into the audited line structure (see mapping below).
A14: Funds presented each year (blank cell = fund not shown as a separate column that year; its balances are within Nonmajor or another column)
A16: Fund | B16: FY2015 | C16: FY2016 | D16: FY2017 | E16: FY2018 | F16: FY2019 | G16: FY2020 | H16: FY2021 | I16: FY2022 | J16: FY2023 | K16: FY2024 | L16: FY2025
A17: General | B17: ✓ | C17: ✓ | D17: ✓ | E17: ✓ | F17: ✓ | G17: ✓ | H17: ✓ | I17: ✓ | J17: ✓ | K17: ✓ | L17: ✓
A18: Physical Plant and Equipment Levy | B18: ✓ | C18: ✓ | D18: ✓ | E18: ✓ | F18: ✓ | G18: ✓ | H18: ✓ | I18: ✓ | J18: ✓ | L18: ✓
A19: Capital Projects | B19: ✓ | C19: ✓ | D19: ✓ | E19: ✓ | F19: ✓ | G19: ✓ | H19: ✓ | I19: ✓ | J19: ✓ | K19: ✓ | L19: ✓
A20: Debt Service | E20: ✓ | F20: ✓ | G20: ✓ | H20: ✓ | I20: ✓ | J20: ✓ | L20: ✓
A21: General Obligation Bonds | E21: ✓ | F21: ✓ | G21: ✓ | H21: ✓ | I21: ✓
A22: Management Levy | K22: ✓ | L22: ✓
A23: Nonmajor Governmental Funds | B23: ✓ | C23: ✓ | D23: ✓ | E23: ✓ | F23: ✓ | G23: ✓ | H23: ✓ | I23: ✓ | J23: ✓ | K23: ✓ | L23: ✓
A24: Total Governmental Funds | B24: ✓ | C24: ✓ | D24: ✓ | E24: ✓ | F24: ✓ | G24: ✓ | H24: ✓ | I24: ✓ | J24: ✓ | K24: ✓ | L24: ✓
A26: FY2025 fund mapping (district CSV → audited fund column)
A27: General Fund → General; PPEL Fund → Physical Plant and Equipment Levy; Management Levy Fund → Management Levy
A28: SAVE (Statewide Sales & Services Tax) + Other Capital Project Funds → Capital Projects; Debt Service Fund → Debt Service
A29: Non-Fiduciary Scholarship, Student Activity, Entrepreneurial Education, PERL, AEA (Sp Ed / JH), Support Trust, Disaster Recovery, Library Levy, Permanent Funds → Nonmajor Governmental Funds
A30: Excluded (not part of the governmental funds balance sheet): Enterprise, Internal Service, Trust and Custodial funds.
A32: FY2025 line reclassifications to fit the audited structure
A33: • Property tax receivable split into current / succeeding year using the succeeding-year property-tax deferred inflow.
A34: • Income surtax receivable separated from intergovernmental receivables (= income-surtax deferred inflow).
A35: • Inventories folded into Prepaid items (both nonspendable). Restricted cash combined into Cash.
A36: • Small deferred outflow of resources (General Fund only) folded into Other receivables to preserve the balance.
A37: • Restricted fund-balance sub-categories aggregated into a single Restricted line (matching FY2015–FY2023 presentation).
A38: • General Obligation Bonds capital fund is within Other Capital Project Funds in FY2025 (no separate column).
... A41: individual fund columns equals the Total Governmental Funds column for each year FY2015–FY2025.

Sheet Cash by Fund
A1: Iowa City Community School District
A2: Cash, cash equivalents and investments by fund over time
A3: General (US dollars)
A5: As of June 30 | B5: FY2015 | C5: FY2016 | D5: FY2017 | E5: FY2018 | F5: FY2019 | G5: FY2020 | H5: FY2021 | I5: FY2022 | J5: FY2023 | K5: FY2024 | L5: FY2025
A6: Cash, cash equivalents and investments by fund
A7: General | B7: =General!B7 -> 25599301 | C7: =General!C7 -> 33270812 | D7: =General!D7 -> 36965401 | E7: =General!E7 -> 35749416 | F7: =General!F7 -> 29661358 | G7: =General!G7 -> 24963852 | H7: =General!H7 -> 21761592 | I7: =General!I7 -> 21475952 | ... L7: =General!L7 -> 43685677
A8: PPEL | B8: =PPEL!B7 -> 10745260 | C8: =PPEL!C7 -> 6751910 | D8: =PPEL!D7 -> 1507984 | E8: =PPEL!E7 -> 1569693 | F8: =PPEL!F7 -> 1488097 | G8: =PPEL!G7 -> 2096950 | H8: =PPEL!H7 -> 3013495 | I8: =PPEL!I7 -> 9862780 | ... L8: =PPEL!L7 -> 9749455.3
A9: Capital Projects | B9: ='Capital Projects'!B7 -> 8364423 | C9: ='Capital Projects'!C7 -> 24869975 | D9: ='Capital Projects'!D7 -> 6821801 | E9: ='Capital Projects'!E7 -> 6411450 | F9: ='Capital Projects'!F7 -> 0 | G9: ='Capital Projects'!G7 -> 0 | H9: ='Capital Projects'!H7 -> 0 | I9: ='Capital Projects'!I7 -> 0 | ... L9: ='Capital Projects'!L7 -> 9638851.6
A10: Debt Service | B10: ='Debt Service'!B7 -> 0 | C10: ='Debt Service'!C7 -> 0 | D10: ='Debt Service'!D7 -> 0 | E10: ='Debt Service'!E7 -> 402793 | F10: ='Debt Service'!F7 -> 774465 | G10: ='Debt Service'!G7 -> 111836 | H10: ='Debt Service'!H7 -> 611235 | I10: ='Debt Service'!I7 -> 930982 | ... L10: ='Debt Service'!L7 -> 150040.26
A11: GO Bonds | B11: ='GO Bonds'!B7 -> 0 | C11: ='GO Bonds'!C7 -> 0 | D11: ='GO Bonds'!D7 -> 0 | E11: ='GO Bonds'!E7 -> 53638555 | F11: ='GO Bonds'!F7 -> 70679827 | G11: ='GO Bonds'!G7 -> 72977150 | H11: ='GO Bonds'!H7 -> 25455199 | I11: ='GO Bonds'!I7 -> 9241045 | ... L11: ='GO Bonds'!L7 -> 0
A12: Management Levy | B12: ='Management Levy'!B7 -> 0 | C12: ='Management Levy'!C7 -> 0 | D12: ='Management Levy'!D7 -> 0 | E12: ='Management Levy'!E7 -> 0 | F12: ='Management Levy'!F7 -> 0 | G12: ='Management Levy'!G7 -> 0 | H12: ='Management Levy'!H7 -> 0 | I12: ='Management Levy'!I7 -> 0 | ... L12: ='Management Levy'!L7 -> 5560131.4
A13: Nonmajor | B13: =Nonmajor!B7 -> 3353218 | C13: =Nonmajor!C7 -> 3373663 | D13: =Nonmajor!D7 -> 3448648 | E13: =Nonmajor!E7 -> 4041715 | F13: =Nonmajor!F7 -> 3610902 | G13: =Nonmajor!G7 -> 2440352 | H13: =Nonmajor!H7 -> 2899975 | I13: =Nonmajor!I7 -> 1742298 | ... L13: =Nonmajor!L7 -> 1009917.3
A14: Total Governmental | B14: ='Total Governmental'!B7 -> 48062202 | C14: ='Total Governmental'!C7 -> 68266360 | D14: ='Total Governmental'!D7 -> 48743834 | E14: ='Total Governmental'!E7 -> 101813622 | F14: ='Total Governmental'!F7 -> 106214649 | G14: ='Total Governmental'!G7 -> 102590140 | H14: ='Total Governmental'!H7 -> 53741496 | I14: ='Total Governmental'!I7 -> 43253057 | ... L14: ='Total Governmental'!L7 -> 69794073
A18: Vs year prior | B18: FY2015 | C18: FY2016 | D18: FY2017 | E18: FY2018 | F18: FY2019 | G18: FY2020 | H18: FY2021 | I18: FY2022 | J18: FY2023 | K18: FY2024 | L18: FY2025
A19: Cash, cash equivalents and investments by fund
A20: General | C20: =C7-B7 -> 7671511 | D20: =D7-C7 -> 3694589 | E20: =E7-D7 -> -1215985 | F20: =F7-E7 -> -6088058 | G20: =G7-F7 -> -4697506 | H20: =H7-G7 -> -3202260 | I20: =I7-H7 -> -285640 | J20: =J7-I7 -> -2463272 | ... L20: =L7-K7 -> 21148685
A21: PPEL | C21: =C8-B8 -> -3993350 | D21: =D8-C8 -> -5243926 | E21: =E8-D8 -> 61709 | F21: =F8-E8 -> -81596 | G21: =G8-F8 -> 608853 | H21: =H8-G8 -> 916545 | I21: =I8-H8 -> 6849285 | J21: =J8-I8 -> 2073972 | ... L21: =L8-K8 -> 9749455.3
A22: Capital Projects | C22: =C9-B9 -> 16505552 | D22: =D9-C9 -> -18048174 | E22: =E9-D9 -> -410351 | F22: =F9-E9 -> -6411450 | G22: =G9-F9 -> 0 | H22: =H9-G9 -> 0 | I22: =I9-H9 -> 0 | J22: =J9-I9 -> 0 | ... L22: =L9-K9 -> -20111872
A23: Debt Service | C23: =C10-B10 -> 0 | D23: =D10-C10 -> 0 | E23: =E10-D10 -> 402793 | F23: =F10-E10 -> 371672 | G23: =G10-F10 -> -662629 | H23: =H10-G10 -> 499399 | I23: =I10-H10 -> 319747 | J23: =J10-I10 -> -66471 | ... L23: =L10-K10 -> 150040.26
A24: GO Bonds | C24: =C11-B11 -> 0 | D24: =D11-C11 -> 0 | E24: =E11-D11 -> 53638555 | F24: =F11-E11 -> 17041272 | G24: =G11-F11 -> 2297323 | H24: =H11-G11 -> -47521951 | I24: =I11-H11 -> -16214154 | J24: =J11-I11 -> -9241045 | ... L24: =L11-K11 -> 0
A25: Management Levy | C25: =C12-B12 -> 0 | D25: =D12-C12 -> 0 | E25: =E12-D12 -> 0 | F25: =F12-E12 -> 0 | G25: =G12-F12 -> 0 | H25: =H12-G12 -> 0 | I25: =I12-H12 -> 0 | J25: =J12-I12 -> 0 | ... L25: =L12-K12 -> -7517477.6
A26: Nonmajor | C26: =C13-B13 -> 20445 | D26: =D13-C13 -> 74985 | E26: =E13-D13 -> 593067 | F26: =F13-E13 -> -430813 | G26: =G13-F13 -> -1170550 | H26: =H13-G13 -> 459623 | I26: =I13-H13 -> -1157677 | J26: =J13-I13 -> 2085341 | ... L26: =L13-K13 -> -863562.7
A27: Total Governmental | C27: =C14-B14 -> 20204158 | D27: =D14-C14 -> -19522526 | E27: =E14-D14 -> 53069788 | F27: =F14-E14 -> 4401027 | G27: =G14-F14 -> -3624509 | H27: =H14-G14 -> -48848644 | I27: =I14-H14 -> -10488439 | J27: =J14-I14 -> -7611475 | ... L27: =L14-K14 -> 2555267.9

Sheet General
A1: Iowa City Community School District
A2: Balance Sheet — Governmental Funds
A3: General (US dollars)
A5: As of June 30 | B5: FY2015 | C5: FY2016 | D5: FY2017 | E5: FY2018 | F5: FY2019 | G5: FY2020 | H5: FY2021 | I5: FY2022 | J5: FY2023 | K5: FY2024 | L5: FY2025
A6: ASSETS
A7: Cash, cash equivalents and investments | B7: 25599301 | C7: 33270812 | D7: 36965401 | E7: 35749416 | F7: 29661358 | G7: 24963852 | H7: 21761592 | I7: 21475952 | J7: 19012680 | K7: 22536992 | L7: 43685677
A8: Restricted cash
A9: Property tax receivable - current year | B9: 232369 | C9: 200376 | D9: 172824 | E9: 248698 | F9: 226346 | G9: 419384 | H9: 560338 | I9: 234203 | J9: 366102 | K9: 429762 | L9: 379454.26
A10: Property tax receivable - succeeding year | B10: 56420267 | C10: 60238767 | D10: 62483923 | E10: 63927908 | F10: 65789035 | G10: 72666630 | H10: 72389732 | I10: 74768537 | J10: 75474753 | K10: 84046760 | L10: 83672537
A11: Income surtax receivable | B11: 6270674 | C11: 6393586 | D11: 6816288 | E11: 6820672 | F11: 7117360 | G11: 7403410 | H11: 6692192 | I11: 7824520 | J11: 7976285 | K11: 6986431 | L11: 7070437
A12: Sales tax receivable
A13: Other receivables | B13: 786056 | C13: 173561 | D13: 147116 | E13: 343272 | F13: 702720 | G13: 2155541 | H13: 996184 | I13: 223250 | J13: 641083 | K13: 385129 | L13: 513783.4
A14: Due from other governments | B14: 2148465 | C14: 1978107 | D14: 1966701 | E14: 1988224 | F14: 2373369 | G14: 2252396 | H14: 10458625 | I14: 7722440 | J14: 14223011 | K14: 5626319 | L14: 2568340
A15: Due from other funds | B15: 1329952 | C15: 11132 | D15: 750616 | E15: 93140 | F15: 27801 | G15: 275994 | H15: 150423 | I15: 177298 | J15: 156679 | K15: 29093296 | L15: 974445.71
A16: Prepaid items | B16: 1095801 | C16: 1127628 | D16: 1251954 | E16: 1395556 | F16: 1472184 | G16: 1552575 | H16: 1317074 | I16: 1738981 | J16: 1702154 | K16: 67836 | L16: 1276719.8
A17: Total assets | B17: =B7+B8+B9+B10+B11+B12+B13+B14+B15+B16 -> 93882885 | C17: =C7+C8+C9+C10+C11+C12+C13+C14+C15+C16 -> 103393969 | D17: =D7+D8+D9+D10+D11+D12+D13+D14+D15+D16 -> 110554823 | E17: =E7+E8+E9+E10+E11+E12+E13+E14+E15+E16 -> 110566886 | F17: =F7+F8+F9+F10+F11+F12+F13+F14+F15+F16 -> 107370173 | G17: =G7+G8+G9+G10+G11+G12+G13+G14+G15+G16 -> 111689782 | H17: =H7+H8+H9+H10+H11+H12+H13+H14+H15+H16 -> 114326160 | I17: =I7+I8+I9+I10+I11+I12+I13+I14+I15+I16 -> 114165181 | ... L17: =L7+L8+L9+L10+L11+L12+L13+L14+L15+L16 -> 1.4014139e+08
A18: LIABILITIES
A19: Accounts payable | B19: 2013166 | C19: 1895636 | D19: 2636705 | E19: 2776112 | F19: 2061443 | G19: 2416119 | H19: 1763278 | I19: 1933142 | J19: 1431069 | K19: 1735139 | L19: 3121264.6
A20: Salaries and benefits payable / accrued liabilities | B20: 13190317 | C20: 13706046 | D20: 14762330 | E20: 15908169 | F20: 17455439 | G20: 16465994 | H20: 17373534 | I20: 19286079 | J20: 19887707 | K20: 17190017 | L20: 26795468
A21: Due to other funds | B21: 2552 | C21: 661001 | D21: 10572 | E21: 8086 | F21: 17064 | G21: 29976 | H21: 22924 | I21: 71144 | J21: 1000000 | K21: 20073735
A22: Due to fiduciary funds | G22: 3120
A23: Unearned revenue | B23: 41627 | C23: 68582 | D23: 11900 | E23: 14516 | F23: 29788 | G23: 1464393 | H23: 194350 | I23: 218705 | J23: 1306772
A24: Total liabilities | B24: =B19+B20+B21+B22+B23 -> 15247662 | C24: =C19+C20+C21+C22+C23 -> 16331265 | D24: =D19+D20+D21+D22+D23 -> 17421507 | E24: =E19+E20+E21+E22+E23 -> 18706883 | F24: =F19+F20+F21+F22+F23 -> 19563734 | G24: =G19+G20+G21+G22+G23 -> 20379602 | H24: =H19+H20+H21+H22+H23 -> 19354086 | I24: =I19+I20+I21+I22+I23 -> 21509070 | ... L24: =L19+L20+L21+L22+L23 -> 29916732
A25: DEFERRED INFLOWS OF RESOURCES
A26: Unavailable revenue - property tax | B26: 56420267 | C26: 60238767 | D26: 62483923 | E26: 63927908 | F26: 65789035 | G26: 72666630 | H26: 72389732 | I26: 74768537 | J26: 75474753 | K26: 84046760 | L26: 83672537
A27: Unavailable revenue - income surtax | B27: 6270674 | C27: 6393586 | D27: 6816288 | E27: 6820672 | F27: 7117360 | G27: 7403410 | H27: 6692192 | I27: 7824520 | J27: 7976285 | K27: 6986431 | L27: 7070437
A28: Unavailable revenue - sales tax
A29: Unavailable revenue - federal sources | J29: 2324940
A30: Unavailable revenue - other | K30: 87390 | L30: 1188013.1
A31: Total deferred inflows of resources | B31: =B26+B27+B28+B29+B30 -> 62690941 | C31: =C26+C27+C28+C29+C30 -> 66632353 | D31: =D26+D27+D28+D29+D30 -> 69300211 | E31: =E26+E27+E28+E29+E30 -> 70748580 | F31: =F26+F27+F28+F29+F30 -> 72906395 | G31: =G26+G27+G28+G29+G30 -> 80070040 | H31: =H26+H27+H28+H29+H30 -> 79081924 | I31: =I26+I27+I28+I29+I30 -> 82593057 | ... L31: =L26+L27+L28+L29+L30 -> 91930987
A32: FUND BALANCES
A33: Nonspendable | B33: 1095801 | C33: 1127628 | D33: 1251954 | E33: 1395556 | F33: 1472184 | G33: 1552575 | H33: 1316399 | I33: 1738981 | J33: 1702154 | K33: 67836 | L33: 1276719.8
A34: Restricted | B34: 3303867 | C34: 3963463 | D34: 4030600 | E34: 2478299 | F34: 2157358 | G34: 2811326 | H34: 2920281 | I34: 2967523 | J34: 3488724 | K34: 2703361 | L34: 4745545.3
A35: Committed
A36: Assigned
A37: Unassigned | B37: 11544614 | C37: 15339260 | D37: 18550551 | E37: 17237568 | F37: 11270502 | G37: 6876239 | H37: 11653470 | I37: 5356550 | J37: 4960343 | K37: 16281856 | L37: 12271410
A38: Total fund balances | B38: =B33+B34+B35+B36+B37 -> 15944282 | C38: =C33+C34+C35+C36+C37 -> 20430351 | D38: =D33+D34+D35+D36+D37 -> 23833105 | E38: =E33+E34+E35+E36+E37 -> 21111423 | F38: =F33+F34+F35+F36+F37 -> 14900044 | G38: =G33+G34+G35+G36+G37 -> 11240140 | H38: =H33+H34+H35+H36+H37 -> 15890150 | I38: =I33+I34+I35+I36+I37 -> 10063054 | ... L38: =L33+L34+L35+L36+L37 -> 18293675
A39: Total liabilities, deferred inflows and fund balances | B39: =B24+B31+B38 -> 93882885 | C39: =C24+C31+C38 -> 103393969 | D39: =D24+D31+D38 -> 110554823 | E39: =E24+E31+E38 -> 110566886 | F39: =F24+F31+F38 -> 107370173 | G39: =G24+G31+G38 -> 111689782 | H39: =H24+H31+H38 -> 114326160 | I39: =I24+I31+I38 -> 114165181 | ... L39: =L24+L31+L38 -> 1.4014139e+08
A41: Balance check (Total assets − L − DI − FB) | B41: =B17-B39 -> 0 | C41: =C17-C39 -> 0 | D41: =D17-D39 -> 0 | E41: =E17-E39 -> 0 | F41: =F17-F39 -> 0 | G41: =G17-G39 -> 0 | H41: =H17-H39 -> 0 | I41: =I17-I39 -> 0 | ... L41: =L17-L39 -> 0

Sheet PPEL
A1: Iowa City Community School District
A2: Balance Sheet — Governmental Funds
A3: Physical Plant and Equipment Levy (US dollars)
A5: As of June 30 | B5: FY2015 | C5: FY2016 | D5: FY2017 | E5: FY2018 | F5: FY2019 | G5: FY2020 | H5: FY2021 | I5: FY2022 | J5: FY2023 | K5: FY2024 | L5: FY2025
A6: ASSETS
A7: Cash, cash equivalents and investments | B7: 10745260 | C7: 6751910 | D7: 1507984 | E7: 1569693 | F7: 1488097 | G7: 2096950 | H7: 3013495 | I7: 9862780 | J7: 11936752 | L7: 9749455.3
A8: Restricted cash
A9: Property tax receivable - current year | B9: 37806 | C9: 30974 | D9: 28685 | E9: 39712 | F9: 38136 | G9: 106997 | H9: 96227 | I9: 39784 | J9: 62119 | L9: 63635.51
A10: Property tax receivable - succeeding year | B10: 9352796 | C10: 9984079 | D10: 10403078 | E10: 10927163 | F10: 11411909 | G10: 12105274 | H10: 12507850 | I10: 12577125 | J10: 12500586 | L10: 13043375
A11: Income surtax receivable
A12: Sales tax receivable
A13: Other receivables | I13: 93988
A14: Due from other governments
A15: Due from other funds | H15: 370968 | I15: 307925
A16: Prepaid items | D16: 134863 | E16: 54619 | F16: 48109 | G16: 84369 | H16: 69763 | I16: 62957 | J16: 55253 | L16: 55252.93
A17: Total assets | B17: =B7+B8+B9+B10+B11+B12+B13+B14+B15+B16 -> 20135862 | C17: =C7+C8+C9+C10+C11+C12+C13+C14+C15+C16 -> 16766963 | D17: =D7+D8+D9+D10+D11+D12+D13+D14+D15+D16 -> 12074610 | E17: =E7+E8+E9+E10+E11+E12+E13+E14+E15+E16 -> 12591187 | F17: =F7+F8+F9+F10+F11+F12+F13+F14+F15+F16 -> 12986251 | G17: =G7+G8+G9+G10+G11+G12+G13+G14+G15+G16 -> 14393590 | H17: =H7+H8+H9+H10+H11+H12+H13+H14+H15+H16 -> 16058303 | I17: =I7+I8+I9+I10+I11+I12+I13+I14+I15+I16 -> 22944559 | J17: =J7+J8+J9+J10+J11+J12+J13+J14+J15+J16 -> 24554710 | L17: =L7+L8+L9+L10+L11+L12+L13+L14+L15+L16 -> 22911719
A18: LIABILITIES
A19: Accounts payable | B19: 1310376 | C19: 1925110 | D19: 1211983 | E19: 1044149 | F19: 1018143 | G19: 1466452 | H19: 736623 | I19: 916677 | J19: 432687 | L19: 1514972.1
A20: Salaries and benefits payable / accrued liabilities
A21: Due to other funds | B21: 1154445 | C21: 6185 | D21: 9828 | E21: 22643 | F21: 2315 | G21: 12617 | H21: 8619 | I21: 64198 | J21: 343139
A22: Due to fiduciary funds
A23: Unearned revenue
A24: Total liabilities | B24: =B19+B20+B21+B22+B23 -> 2464821 | C24: =C19+C20+C21+C22+C23 -> 1931295 | D24: =D19+D20+D21+D22+D23 -> 1221811 | E24: =E19+E20+E21+E22+E23 -> 1066792 | F24: =F19+F20+F21+F22+F23 -> 1020458 | G24: =G19+G20+G21+G22+G23 -> 1479069 | H24: =H19+H20+H21+H22+H23 -> 745242 | I24: =I19+I20+I21+I22+I23 -> 980875 | J24: =J19+J20+J21+J22+J23 -> 775826 | L24: =L19+L20+L21+L22+L23 -> 1514972.1
A25: DEFERRED INFLOWS OF RESOURCES
A26: Unavailable revenue - property tax | B26: 9352796 | C26: 9984079 | D26: 10403078 | E26: 10927163 | F26: 11411909 | G26: 12105274 | H26: 12507850 | I26: 12577125 | J26: 12500586 | L26: 13043375
A27: Unavailable revenue - income surtax
A28: Unavailable revenue - sales tax
A29: Unavailable revenue - federal sources
A30: Unavailable revenue - other
A31: Total deferred inflows of resources | B31: =B26+B27+B28+B29+B30 -> 9352796 | C31: =C26+C27+C28+C29+C30 -> 9984079 | D31: =D26+D27+D28+D29+D30 -> 10403078 | E31: =E26+E27+E28+E29+E30 -> 10927163 | F31: =F26+F27+F28+F29+F30 -> 11411909 | G31: =G26+G27+G28+G29+G30 -> 12105274 | H31: =H26+H27+H28+H29+H30 -> 12507850 | I31: =I26+I27+I28+I29+I30 -> 12577125 | J31: =J26+J27+J28+J29+J30 -> 12500586 | L31: =L26+L27+L28+L29+L30 -> 13043375
A32: FUND BALANCES
A33: Nonspendable | D33: 134863 | E33: 54619 | F33: 48109 | G33: 84369 | H33: 69763 | I33: 62957 | J33: 55253 | L33: 55252.93
A34: Restricted | B34: 8318245 | C34: 4851589 | D34: 314858 | E34: 542613 | F34: 505775 | G34: 724878 | H34: 2735448 | I34: 9323602 | J34: 11223045 | L34: 8353371.7
A35: Committed
A36: Assigned
A37: Unassigned | L37: -55252.93
A38: Total fund balances | B38: =B33+B34+B35+B36+B37 -> 8318245 | C38: =C33+C34+C35+C36+C37 -> 4851589 | D38: =D33+D34+D35+D36+D37 -> 449721 | E38: =E33+E34+E35+E36+E37 -> 597232 | F38: =F33+F34+F35+F36+F37 -> 553884 | G38: =G33+G34+G35+G36+G37 -> 809247 | H38: =H33+H34+H35+H36+H37 -> 2805211 | I38: =I33+I34+I35+I36+I37 -> 9386559 | J38: =J33+J34+J35+J36+J37 -> 11278298 | L38: =L33+L34+L35+L36+L37 -> 8353371.7
A39: Total liabilities, deferred inflows and fund balances | B39: =B24+B31+B38 -> 20135862 | C39: =C24+C31+C38 -> 16766963 | D39: =D24+D31+D38 -> 12074610 | E39: =E24+E31+E38 -> 12591187 | F39: =F24+F31+F38 -> 12986251 | G39: =G24+G31+G38 -> 14393590 | H39: =H24+H31+H38 -> 16058303 | I39: =I24+I31+I38 -> 22944559 | J39: =J24+J31+J38 -> 24554710 | L39: =L24+L31+L38 -> 22911719
A41: Balance check (Total assets − L − DI − FB) | B41: =B17-B39 -> 0 | C41: =C17-C39 -> 0 | D41: =D17-D39 -> 0 | E41: =E17-E39 -> 0 | F41: =F17-F39 -> 0 | G41: =G17-G39 -> 0 | H41: =H17-H39 -> 0 | I41: =I17-I39 -> 0 | J41: =J17-J39 -> 0 | L41: =L17-L39 -> 0

Sheet Capital Projects
A1: Iowa City Community School District
A2: Balance Sheet — Governmental Funds
A3: Capital Projects (US dollars)
A5: As of June 30 | B5: FY2015 | C5: FY2016 | D5: FY2017 | E5: FY2018 | F5: FY2019 | G5: FY2020 | H5: FY2021 | I5: FY2022 | J5: FY2023 | K5: FY2024 | L5: FY2025
A6: ASSETS
A7: Cash, cash equivalents and investments | B7: 8364423 | C7: 24869975 | D7: 6821801 | E7: 6411450 | K7: 29750724 | L7: 9638851.6
A8: Restricted cash | C8: 5587205 | D8: 5587205 | E8: 5587205 | F8: 3205668 | G8: 2941742 | H8: 1770109 | I8: 2991866 | J8: 87438769
A9: Property tax receivable - current year | K9: 69409
A10: Property tax receivable - succeeding year | K10: 13106246
A11: Income surtax receivable
A12: Sales tax receivable | B12: 600000 | C12: 500000 | D12: 520000 | E12: 670000 | F12: 424339 | G12: 434796 | H12: 2093103 | I12: 2400991
A13: Other receivables
A14: Due from other governments | B14: 1935743 | C14: 2088780 | D14: 1088388 | E14: 1103259 | F14: 1155570 | G14: 1246881 | H14: 1217850 | I14: 1207537 | J14: 1387439 | K14: 1750343 | L14: 1994425.4
A15: Due from other funds | C15: 571353 | H15: 22924 | I15: 71703 | J15: 302077 | K15: 8492371
A16: Prepaid items | B16: 1540 | C16: 1310 | D16: 133110 | E16: 83073 | F16: 46770 | G16: 12778 | H16: 276213 | I16: 68695 | J16: 115388 | K16: 186460 | L16: 5626.87
A17: Total assets | B17: =B7+B8+B9+B10+B11+B12+B13+B14+B15+B16 -> 10901706 | C17: =C7+C8+C9+C10+C11+C12+C13+C14+C15+C16 -> 33618623 | D17: =D7+D8+D9+D10+D11+D12+D13+D14+D15+D16 -> 14150504 | E17: =E7+E8+E9+E10+E11+E12+E13+E14+E15+E16 -> 13854987 | F17: =F7+F8+F9+F10+F11+F12+F13+F14+F15+F16 -> 4832347 | G17: =G7+G8+G9+G10+G11+G12+G13+G14+G15+G16 -> 4636197 | H17: =H7+H8+H9+H10+H11+H12+H13+H14+H15+H16 -> 5380199 | I17: =I7+I8+I9+I10+I11+I12+I13+I14+I15+I16 -> 6740792 | ... L17: =L7+L8+L9+L10+L11+L12+L13+L14+L15+L16 -> 11638904
A18: LIABILITIES
A19: Accounts payable | B19: 5369297 | C19: 7094040 | D19: 4320915 | E19: 3290977 | F19: 261070 | G19: 17782 | H19: 1857138 | I19: 605023 | J19: 5417498 | K19: 10179103 | L19: 2359126.3
A20: Salaries and benefits payable / accrued liabilities | B20: 19469 | C20: 17814 | D20: 15306 | E20: 18944 | F20: 21082 | G20: 25352 | H20: 20151 | I20: 24877 | J20: 25864 | K20: 17222 | L20: 69581.37
A21: Due to other funds | B21: 33476 | D21: 11741 | E21: 37603 | F21: 21076 | G21: 28927 | J21: 78982 | K21: 1103189
A22: Due to fiduciary funds
A23: Unearned revenue
A24: Total liabilities | B24: =B19+B20+B21+B22+B23 -> 5422242 | C24: =C19+C20+C21+C22+C23 -> 7111854 | D24: =D19+D20+D21+D22+D23 -> 4347962 | E24: =E19+E20+E21+E22+E23 -> 3347524 | F24: =F19+F20+F21+F22+F23 -> 303228 | G24: =G19+G20+G21+G22+G23 -> 72061 | H24: =H19+H20+H21+H22+H23 -> 1877289 | I24: =I19+I20+I21+I22+I23 -> 629900 | ... L24: =L19+L20+L21+L22+L23 -> 2428707.7
A25: DEFERRED INFLOWS OF RESOURCES
A26: Unavailable revenue - property tax | K26: 13106246
A27: Unavailable revenue - income surtax
A28: Unavailable revenue - sales tax | B28: 600000 | C28: 500000 | D28: 520000 | E28: 670000 | F28: 424339 | G28: 434796 | H28: 2093103 | I28: 2400991
A29: Unavailable revenue - federal sources
A30: Unavailable revenue - other
A31: Total deferred inflows of resources | B31: =B26+B27+B28+B29+B30 -> 600000 | C31: =C26+C27+C28+C29+C30 -> 500000 | D31: =D26+D27+D28+D29+D30 -> 520000 | E31: =E26+E27+E28+E29+E30 -> 670000 | F31: =F26+F27+F28+F29+F30 -> 424339 | G31: =G26+G27+G28+G29+G30 -> 434796 | H31: =H26+H27+H28+H29+H30 -> 2093103 | I31: =I26+I27+I28+I29+I30 -> 2400991 | ... L31: =L26+L27+L28+L29+L30 -> 0
A32: FUND BALANCES
A33: Nonspendable | B33: 1540 | C33: 1310 | D33: 133110 | E33: 83073 | F33: 46770 | G33: 12778 | H33: 276213 | I33: 68695 | J33: 115388 | K33: 186460 | L33: 5626.87
A34: Restricted | B34: 4877924 | C34: 26005459 | D34: 9149432 | E34: 9754390 | F34: 4058010 | G34: 4116562 | H34: 1133594 | I34: 3641206 | J34: 83605941 | K34: 28763333 | L34: 10120664
A35: Committed
A36: Assigned
A37: Unassigned | L37: -916094.72
A38: Total fund balances | B38: =B33+B34+B35+B36+B37 -> 4879464 | C38: =C33+C34+C35+C36+C37 -> 26006769 | D38: =D33+D34+D35+D36+D37 -> 9282542 | E38: =E33+E34+E35+E36+E37 -> 9837463 | F38: =F33+F34+F35+F36+F37 -> 4104780 | G38: =G33+G34+G35+G36+G37 -> 4129340 | H38: =H33+H34+H35+H36+H37 -> 1409807 | I38: =I33+I34+I35+I36+I37 -> 3709901 | ... L38: =L33+L34+L35+L36+L37 -> 9210196.2
A39: Total liabilities, deferred inflows and fund balances | B39: =B24+B31+B38 -> 10901706 | C39: =C24+C31+C38 -> 33618623 | D39: =D24+D31+D38 -> 14150504 | E39: =E24+E31+E38 -> 13854987 | F39: =F24+F31+F38 -> 4832347 | G39: =G24+G31+G38 -> 4636197 | H39: =H24+H31+H38 -> 5380199 | I39: =I24+I31+I38 -> 6740792 | ... L39: =L24+L31+L38 -> 11638904
A41: Balance check (Total assets − L − DI − FB) | B41: =B17-B39 -> 0 | C41: =C17-C39 -> 0 | D41: =D17-D39 -> 0 | E41: =E17-E39 -> 0 | F41: =F17-F39 -> 0 | G41: =G17-G39 -> 0 | H41: =H17-H39 -> 0 | I41: =I17-I39 -> 0 | ... L41: =L17-L39 -> 0

Sheet Debt Service
A1: Iowa City Community School District
A2: Balance Sheet — Governmental Funds
A3: Debt Service (US dollars)
A5: As of June 30 | B5: FY2015 | C5: FY2016 | D5: FY2017 | E5: FY2018 | F5: FY2019 | G5: FY2020 | H5: FY2021 | I5: FY2022 | J5: FY2023 | K5: FY2024 | L5: FY2025
A6: ASSETS
A7: Cash, cash equivalents and investments | E7: 402793 | F7: 774465 | G7: 111836 | H7: 611235 | I7: 930982 | J7: 864511 | L7: 150040.26
A8: Restricted cash
A9: Property tax receivable - current year | E9: 12572 | F9: 44653 | G9: 92816 | H9: 103017 | I9: 41125 | J9: 64060 | L9: 65394.43
A10: Property tax receivable - succeeding year | E10: 12794596 | F10: 9899455 | G10: 12959530 | H10: 12929522 | I10: 12970254 | J10: 12832637 | L10: 13403898
A11: Income surtax receivable
A12: Sales tax receivable
A13: Other receivables
A14: Due from other governments
A15: Due from other funds
A16: Prepaid items
A17: Total assets | E17: =E7+E8+E9+E10+E11+E12+E13+E14+E15+E16 -> 13209961 | F17: =F7+F8+F9+F10+F11+F12+F13+F14+F15+F16 -> 10718573 | G17: =G7+G8+G9+G10+G11+G12+G13+G14+G15+G16 -> 13164182 | H17: =H7+H8+H9+H10+H11+H12+H13+H14+H15+H16 -> 13643774 | I17: =I7+I8+I9+I10+I11+I12+I13+I14+I15+I16 -> 13942361 | J17: =J7+J8+J9+J10+J11+J12+J13+J14+J15+J16 -> 13761208 | L17: =L7+L8+L9+L10+L11+L12+L13+L14+L15+L16 -> 13619333
A18: LIABILITIES
A19: Accounts payable
A20: Salaries and benefits payable / accrued liabilities
A21: Due to other funds
A22: Due to fiduciary funds
A23: Unearned revenue
A24: Total liabilities | E24: =E19+E20+E21+E22+E23 -> 0 | F24: =F19+F20+F21+F22+F23 -> 0 | G24: =G19+G20+G21+G22+G23 -> 0 | H24: =H19+H20+H21+H22+H23 -> 0 | I24: =I19+I20+I21+I22+I23 -> 0 | J24: =J19+J20+J21+J22+J23 -> 0 | L24: =L19+L20+L21+L22+L23 -> 0
A25: DEFERRED INFLOWS OF RESOURCES
A26: Unavailable revenue - property tax | E26: 12794596 | F26: 9899455 | G26: 12959530 | H26: 12929522 | I26: 12970254 | J26: 12832637 | L26: 13403898
A27: Unavailable revenue - income surtax
A28: Unavailable revenue - sales tax
A29: Unavailable revenue - federal sources
A30: Unavailable revenue - other
A31: Total deferred inflows of resources | E31: =E26+E27+E28+E29+E30 -> 12794596 | F31: =F26+F27+F28+F29+F30 -> 9899455 | G31: =G26+G27+G28+G29+G30 -> 12959530 | H31: =H26+H27+H28+H29+H30 -> 12929522 | I31: =I26+I27+I28+I29+I30 -> 12970254 | J31: =J26+J27+J28+J29+J30 -> 12832637 | L31: =L26+L27+L28+L29+L30 -> 13403898
A32: FUND BALANCES
A33: Nonspendable
A34: Restricted | E34: 415365 | F34: 819118 | G34: 204652 | H34: 714252 | I34: 972107 | J34: 928571 | L34: 215434.69
A35: Committed
A36: Assigned
A37: Unassigned
A38: Total fund balances | E38: =E33+E34+E35+E36+E37 -> 415365 | F38: =F33+F34+F35+F36+F37 -> 819118 | G38: =G33+G34+G35+G36+G37 -> 204652 | H38: =H33+H34+H35+H36+H37 -> 714252 | I38: =I33+I34+I35+I36+I37 -> 972107 | J38: =J33+J34+J35+J36+J37 -> 928571 | L38: =L33+L34+L35+L36+L37 -> 215434.69
A39: Total liabilities, deferred inflows and fund balances | E39: =E24+E31+E38 -> 13209961 | F39: =F24+F31+F38 -> 10718573 | G39: =G24+G31+G38 -> 13164182 | H39: =H24+H31+H38 -> 13643774 | I39: =I24+I31+I38 -> 13942361 | J39: =J24+J31+J38 -> 13761208 | L39: =L24+L31+L38 -> 13619333
A41: Balance check (Total assets − L − DI − FB) | E41: =E17-E39 -> 0 | F41: =F17-F39 -> 0 | G41: =G17-G39 -> 0 | H41: =H17-H39 -> 0 | I41: =I17-I39 -> 0 | J41: =J17-J39 -> 0 | L41: =L17-L39 -> 0

Sheet GO Bonds
A1: Iowa City Community School District
A2: Balance Sheet — Governmental Funds
A3: General Obligation Bonds (US dollars)
A5: As of June 30 | B5: FY2015 | C5: FY2016 | D5: FY2017 | E5: FY2018 | F5: FY2019 | G5: FY2020 | H5: FY2021 | I5: FY2022 | J5: FY2023 | K5: FY2024 | L5: FY2025
A6: ASSETS
A7: Cash, cash equivalents and investments | E7: 53638555 | F7: 70679827 | G7: 72977150 | H7: 25455199 | I7: 9241045
A8: Restricted cash
A9: Property tax receivable - current year
A10: Property tax receivable - succeeding year
A11: Income surtax receivable
A12: Sales tax receivable
A13: Other receivables
A14: Due from other governments
A15: Due from other funds
A16: Prepaid items | G16: 338 | H16: 337
A17: Total assets | E17: =E7+E8+E9+E10+E11+E12+E13+E14+E15+E16 -> 53638555 | F17: =F7+F8+F9+F10+F11+F12+F13+F14+F15+F16 -> 70679827 | G17: =G7+G8+G9+G10+G11+G12+G13+G14+G15+G16 -> 72977488 | H17: =H7+H8+H9+H10+H11+H12+H13+H14+H15+H16 -> 25455536 | I17: =I7+I8+I9+I10+I11+I12+I13+I14+I15+I16 -> 9241045
A18: LIABILITIES
A19: Accounts payable | E19: 3491737 | F19: 10700702 | G19: 9128881 | H19: 4955176 | I19: 2296139
A20: Salaries and benefits payable / accrued liabilities | G20: 2472 | H20: 2010
A21: Due to other funds | F21: 1068 | G21: 7788 | H21: 1179 | I21: 174
A22: Due to fiduciary funds
A23: Unearned revenue
A24: Total liabilities | E24: =E19+E20+E21+E22+E23 -> 3491737 | F24: =F19+F20+F21+F22+F23 -> 10701770 | G24: =G19+G20+G21+G22+G23 -> 9139141 | H24: =H19+H20+H21+H22+H23 -> 4958365 | I24: =I19+I20+I21+I22+I23 -> 2296313
A25: DEFERRED INFLOWS OF RESOURCES
A26: Unavailable revenue - property tax
A27: Unavailable revenue - income surtax
A28: Unavailable revenue - sales tax
A29: Unavailable revenue - federal sources
A30: Unavailable revenue - other
A31: Total deferred inflows of resources | E31: =E26+E27+E28+E29+E30 -> 0 | F31: =F26+F27+F28+F29+F30 -> 0 | G31: =G26+G27+G28+G29+G30 -> 0 | H31: =H26+H27+H28+H29+H30 -> 0 | I31: =I26+I27+I28+I29+I30 -> 0
A32: FUND BALANCES
A33: Nonspendable | G33: 338 | H33: 337
A34: Restricted | E34: 50146818 | F34: 59978057 | G34: 63838009 | H34: 20496834 | I34: 6944732
A35: Committed
A36: Assigned
A37: Unassigned
A38: Total fund balances | E38: =E33+E34+E35+E36+E37 -> 50146818 | F38: =F33+F34+F35+F36+F37 -> 59978057 | G38: =G33+G34+G35+G36+G37 -> 63838347 | H38: =H33+H34+H35+H36+H37 -> 20497171 | I38: =I33+I34+I35+I36+I37 -> 6944732
A39: Total liabilities, deferred inflows and fund balances | E39: =E24+E31+E38 -> 53638555 | F39: =F24+F31+F38 -> 70679827 | G39: =G24+G31+G38 -> 72977488 | H39: =H24+H31+H38 -> 25455536 | I39: =I24+I31+I38 -> 9241045
A41: Balance check (Total assets − L − DI − FB) | E41: =E17-E39 -> 0 | F41: =F17-F39 -> 0 | G41: =G17-G39 -> 0 | H41: =H17-H39 -> 0 | I41: =I17-I39 -> 0

Sheet Management Levy
A1: Iowa City Community School District
A2: Balance Sheet — Governmental Funds
A3: Management Levy (US dollars)
A5: As of June 30 | B5: FY2015 | C5: FY2016 | D5: FY2017 | E5: FY2018 | F5: FY2019 | G5: FY2020 | H5: FY2021 | I5: FY2022 | J5: FY2023 | K5: FY2024 | L5: FY2025
A6: ASSETS
A7: Cash, cash equivalents and investments | K7: 13077609 | L7: 5560131.4
A8: Restricted cash
A9: Property tax receivable - current year | K9: 76047 | L9: 58601.09
A10: Property tax receivable - succeeding year | K10: 13000005 | L10: 12942151
A11: Income surtax receivable
A12: Sales tax receivable
A13: Other receivables
A14: Due from other governments
A15: Due from other funds | K15: 12788
A16: Prepaid items
A17: Total assets | K17: =K7+K8+K9+K10+K11+K12+K13+K14+K15+K16 -> 26166449 | L17: =L7+L8+L9+L10+L11+L12+L13+L14+L15+L16 -> 18560884
A18: LIABILITIES
A19: Accounts payable
A20: Salaries and benefits payable / accrued liabilities
A21: Due to other funds | K21: 11373033
A22: Due to fiduciary funds
A23: Unearned revenue
A24: Total liabilities | K24: =K19+K20+K21+K22+K23 -> 11373033 | L24: =L19+L20+L21+L22+L23 -> 0
A25: DEFERRED INFLOWS OF RESOURCES
A26: Unavailable revenue - property tax | K26: 13000005 | L26: 12942151
A27: Unavailable revenue - income surtax
A28: Unavailable revenue - sales tax
A29: Unavailable revenue - federal sources
A30: Unavailable revenue - other
A31: Total deferred inflows of resources | K31: =K26+K27+K28+K29+K30 -> 13000005 | L31: =L26+L27+L28+L29+L30 -> 12942151
A32: FUND BALANCES
A33: Nonspendable
A34: Restricted | K34: 1793411 | L34: 5618732.5
A35: Committed
A36: Assigned
A37: Unassigned
A38: Total fund balances | K38: =K33+K34+K35+K36+K37 -> 1793411 | L38: =L33+L34+L35+L36+L37 -> 5618732.5
A39: Total liabilities, deferred inflows and fund balances | K39: =K24+K31+K38 -> 26166449 | L39: =L24+L31+L38 -> 18560884
A41: Balance check (Total assets − L − DI − FB) | K41: =K17-K39 -> 0 | L41: =L17-L39 -> 0

Sheet Nonmajor
A1: Iowa City Community School District
A2: Balance Sheet — Governmental Funds
A3: Nonmajor Governmental Funds (US dollars)
A5: As of June 30 | B5: FY2015 | C5: FY2016 | D5: FY2017 | E5: FY2018 | F5: FY2019 | G5: FY2020 | H5: FY2021 | I5: FY2022 | J5: FY2023 | K5: FY2024 | L5: FY2025
A6: ASSETS
A7: Cash, cash equivalents and investments | B7: 3353218 | C7: 3373663 | D7: 3448648 | E7: 4041715 | F7: 3610902 | G7: 2440352 | H7: 2899975 | I7: 1742298 | J7: 3827639 | K7: 1873480 | L7: 1009917.3
A8: Restricted cash
A9: Property tax receivable - current year | B9: 31520 | C9: 21532 | D9: 21161 | E9: 17918 | F9: 16643 | G9: 50840 | H9: 28898 | I9: 20869 | J9: 25460 | K9: 71252
A10: Property tax receivable - succeeding year | B10: 6282567 | C10: 7371340 | D10: 7793380 | E10: 4699970 | F10: 7999987 | G10: 3749981 | H10: 6449990 | I10: 5200017 | J10: 13348019 | K10: 13468512
A11: Income surtax receivable
A12: Sales tax receivable
A13: Other receivables | D13: 1500 | F13: 33158 | G13: 27498 | H13: 9721 | I13: 40 | J13: 1007 | K13: 40 | L13: 40
A14: Due from other governments
A15: Due from other funds | C15: 89648 | E15: 700 | G15: 54494 | H15: 830 | I15: 1700 | J15: 159383 | L15: 408.62
A16: Prepaid items
A17: Total assets | B17: =B7+B8+B9+B10+B11+B12+B13+B14+B15+B16 -> 9667305 | C17: =C7+C8+C9+C10+C11+C12+C13+C14+C15+C16 -> 10856183 | D17: =D7+D8+D9+D10+D11+D12+D13+D14+D15+D16 -> 11264689 | E17: =E7+E8+E9+E10+E11+E12+E13+E14+E15+E16 -> 8760303 | F17: =F7+F8+F9+F10+F11+F12+F13+F14+F15+F16 -> 11660690 | G17: =G7+G8+G9+G10+G11+G12+G13+G14+G15+G16 -> 6323165 | H17: =H7+H8+H9+H10+H11+H12+H13+H14+H15+H16 -> 9389414 | I17: =I7+I8+I9+I10+I11+I12+I13+I14+I15+I16 -> 6964924 | ... L17: =L7+L8+L9+L10+L11+L12+L13+L14+L15+L16 -> 1010365.9
A18: LIABILITIES
A19: Accounts payable | B19: 109362 | C19: 149198 | D19: 209510 | E19: 304226 | F19: 86825 | G19: 146127 | H19: 151862 | I19: 136184 | J19: 280524 | K19: 3371 | L19: 35511.59
A20: Salaries and benefits payable / accrued liabilities
A21: Due to other funds | B21: 57847 | C21: 1503 | D21: 12828 | E21: 31783 | F21: 18778 | H21: 476363 | I21: 336237 | J21: 87958 | K21: 1547982 | L21: 974854.33
A22: Due to fiduciary funds | F22: 1103
A23: Unearned revenue
A24: Total liabilities | B24: =B19+B20+B21+B22+B23 -> 167209 | C24: =C19+C20+C21+C22+C23 -> 150701 | D24: =D19+D20+D21+D22+D23 -> 222338 | E24: =E19+E20+E21+E22+E23 -> 336009 | F24: =F19+F20+F21+F22+F23 -> 106706 | G24: =G19+G20+G21+G22+G23 -> 146127 | H24: =H19+H20+H21+H22+H23 -> 628225 | I24: =I19+I20+I21+I22+I23 -> 472421 | ... L24: =L19+L20+L21+L22+L23 -> 1010365.9
A25: DEFERRED INFLOWS OF RESOURCES
A26: Unavailable revenue - property tax | B26: 6282567 | C26: 7371340 | D26: 7793380 | E26: 4699970 | F26: 7999987 | G26: 3749981 | H26: 6468845 | I26: 5200017 | J26: 13348019 | K26: 13468512
A27: Unavailable revenue - income surtax
A28: Unavailable revenue - sales tax
A29: Unavailable revenue - federal sources
A30: Unavailable revenue - other
A31: Total deferred inflows of resources | B31: =B26+B27+B28+B29+B30 -> 6282567 | C31: =C26+C27+C28+C29+C30 -> 7371340 | D31: =D26+D27+D28+D29+D30 -> 7793380 | E31: =E26+E27+E28+E29+E30 -> 4699970 | F31: =F26+F27+F28+F29+F30 -> 7999987 | G31: =G26+G27+G28+G29+G30 -> 3749981 | H31: =H26+H27+H28+H29+H30 -> 6468845 | I31: =I26+I27+I28+I29+I30 -> 5200017 | ... L31: =L26+L27+L28+L29+L30 -> 0
A32: FUND BALANCES
A33: Nonspendable
A34: Restricted | B34: 3217529 | C34: 3334142 | D34: 3248971 | E34: 3724324 | F34: 3553997 | G34: 2427057 | H34: 2292344 | I34: 1292486 | J34: 3645007 | K34: 1376800
A35: Committed
A36: Assigned
A37: Unassigned | K37: -983381
A38: Total fund balances | B38: =B33+B34+B35+B36+B37 -> 3217529 | C38: =C33+C34+C35+C36+C37 -> 3334142 | D38: =D33+D34+D35+D36+D37 -> 3248971 | E38: =E33+E34+E35+E36+E37 -> 3724324 | F38: =F33+F34+F35+F36+F37 -> 3553997 | G38: =G33+G34+G35+G36+G37 -> 2427057 | H38: =H33+H34+H35+H36+H37 -> 2292344 | I38: =I33+I34+I35+I36+I37 -> 1292486 | ... L38: =L33+L34+L35+L36+L37 -> 0
A39: Total liabilities, deferred inflows and fund balances | B39: =B24+B31+B38 -> 9667305 | C39: =C24+C31+C38 -> 10856183 | D39: =D24+D31+D38 -> 11264689 | E39: =E24+E31+E38 -> 8760303 | F39: =F24+F31+F38 -> 11660690 | G39: =G24+G31+G38 -> 6323165 | H39: =H24+H31+H38 -> 9389414 | I39: =I24+I31+I38 -> 6964924 | ... L39: =L24+L31+L38 -> 1010365.9
A41: Balance check (Total assets − L − DI − FB) | B41: =B17-B39 -> 0 | C41: =C17-C39 -> 0 | D41: =D17-D39 -> 0 | E41: =E17-E39 -> 0 | F41: =F17-F39 -> 0 | G41: =G17-G39 -> 0 | H41: =H17-H39 -> 0 | I41: =I17-I39 -> 0 | ... L41: =L17-L39 -> 0

Sheet Total Governmental
A1: Iowa City Community School District
A2: Balance Sheet — Governmental Funds
A3: Total Governmental Funds (US dollars)
A5: As of June 30 | B5: FY2015 | C5: FY2016 | D5: FY2017 | E5: FY2018 | F5: FY2019 | G5: FY2020 | H5: FY2021 | I5: FY2022 | J5: FY2023 | K5: FY2024 | L5: FY2025
A6: ASSETS
A7: Cash, cash equivalents and investments | B7: 48062202 | C7: 68266360 | D7: 48743834 | E7: 101813622 | F7: 106214649 | G7: 102590140 | H7: 53741496 | I7: 43253057 | J7: 35641582 | K7: 67238805 | L7: 69794073
A8: Restricted cash | C8: 5587205 | D8: 5587205 | E8: 5587205 | F8: 3205668 | G8: 2941742 | H8: 1770109 | I8: 2991866 | J8: 87438769
A9: Property tax receivable - current year | B9: 301695 | C9: 252882 | D9: 222670 | E9: 318900 | F9: 325778 | G9: 670037 | H9: 788480 | I9: 335981 | J9: 517741 | K9: 646470 | L9: 567085.29
A10: Property tax receivable - succeeding year | B10: 72055630 | C10: 77594186 | D10: 80680381 | E10: 92349637 | F10: 95100386 | G10: 101481415 | H10: 104277094 | I10: 105515933 | J10: 114155995 | K10: 123621523 | L10: 1.2306196e+08
A11: Income surtax receivable | B11: 6270674 | C11: 6393586 | D11: 6816288 | E11: 6820672 | F11: 7117360 | G11: 7403410 | H11: 6692192 | I11: 7824520 | J11: 7976285 | K11: 6986431 | L11: 7070437
A12: Sales tax receivable | B12: 600000 | C12: 500000 | D12: 520000 | E12: 670000 | F12: 424339 | G12: 434796 | H12: 2093103 | I12: 2400991
A13: Other receivables | B13: 786056 | C13: 173561 | D13: 148616 | E13: 343272 | F13: 735878 | G13: 2183039 | H13: 1005905 | I13: 317278 | J13: 642090 | K13: 385169 | L13: 513823.4
A14: Due from other governments | B14: 4084208 | C14: 4066887 | D14: 3055089 | E14: 3091483 | F14: 3528939 | G14: 3499277 | H14: 11676475 | I14: 8929977 | J14: 15610450 | K14: 7376662 | L14: 4562765.4
A15: Due from other funds | B15: 1329952 | C15: 672133 | D15: 750616 | E15: 93840 | F15: 27801 | G15: 330488 | H15: 545145 | I15: 558626 | J15: 618139 | K15: 37598455 | L15: 974854.33
A16: Prepaid items | B16: 1097341 | C16: 1128938 | D16: 1519927 | E16: 1533248 | F16: 1567063 | G16: 1650060 | H16: 1663387 | I16: 1870633 | J16: 1872795 | K16: 254296 | L16: 1337599.6
A17: Total assets | B17: =B7+B8+B9+B10+B11+B12+B13+B14+B15+B16 -> 134587758 | C17: =C7+C8+C9+C10+C11+C12+C13+C14+C15+C16 -> 164635738 | D17: =D7+D8+D9+D10+D11+D12+D13+D14+D15+D16 -> 148044626 | E17: =E7+E8+E9+E10+E11+E12+E13+E14+E15+E16 -> 212621879 | F17: =F7+F8+F9+F10+F11+F12+F13+F14+F15+F16 -> 218247861 | G17: =G7+G8+G9+G10+G11+G12+G13+G14+G15+G16 -> 223184404 | H17: =H7+H8+H9+H10+H11+H12+H13+H14+H15+H16 -> 184253386 | I17: =I7+I8+I9+I10+I11+I12+I13+I14+I15+I16 -> 173998862 | ... L17: =L7+L8+L9+L10+L11+L12+L13+L14+L15+L16 -> 2.078826e+08
A18: LIABILITIES
A19: Accounts payable | B19: 8802201 | C19: 11063984 | D19: 8379113 | E19: 10907201 | F19: 14128183 | G19: 13175361 | H19: 9464077 | I19: 5887165 | J19: 7561778 | K19: 11917613 | L19: 7030874.5
A20: Salaries and benefits payable / accrued liabilities | B20: 13209786 | C20: 13723860 | D20: 14777636 | E20: 15927113 | F20: 17476521 | G20: 16493818 | H20: 17395695 | I20: 19310956 | J20: 19913571 | K20: 17207239 | L20: 26865049
A21: Due to other funds | B21: 1248320 | C21: 668689 | D21: 44969 | E21: 100115 | F21: 60301 | G21: 79308 | H21: 509085 | I21: 471753 | J21: 1510079 | K21: 34097939 | L21: 974854.33
A22: Due to fiduciary funds | F22: 1103 | G22: 3120
A23: Unearned revenue | B23: 41627 | C23: 68582 | D23: 11900 | E23: 14516 | F23: 29788 | G23: 1464393 | H23: 194350 | I23: 218705 | J23: 1306772
A24: Total liabilities | B24: =B19+B20+B21+B22+B23 -> 23301934 | C24: =C19+C20+C21+C22+C23 -> 25525115 | D24: =D19+D20+D21+D22+D23 -> 23213618 | E24: =E19+E20+E21+E22+E23 -> 26948945 | F24: =F19+F20+F21+F22+F23 -> 31695896 | G24: =G19+G20+G21+G22+G23 -> 31216000 | H24: =H19+H20+H21+H22+H23 -> 27563207 | I24: =I19+I20+I21+I22+I23 -> 25888579 | ... L24: =L19+L20+L21+L22+L23 -> 34870778
A25: DEFERRED INFLOWS OF RESOURCES
A26: Unavailable revenue - property tax | B26: 72055630 | C26: 77594186 | D26: 80680381 | E26: 92349637 | F26: 95100386 | G26: 101481415 | H26: 104295949 | I26: 105515933 | J26: 114155995 | K26: 123621523 | L26: 1.2306196e+08
A27: Unavailable revenue - income surtax | B27: 6270674 | C27: 6393586 | D27: 6816288 | E27: 6820672 | F27: 7117360 | G27: 7403410 | H27: 6692192 | I27: 7824520 | J27: 7976285 | K27: 6986431 | L27: 7070437
A28: Unavailable revenue - sales tax | B28: 600000 | C28: 500000 | D28: 520000 | E28: 670000 | F28: 424339 | G28: 434796 | H28: 2093103 | I28: 2400991
A29: Unavailable revenue - federal sources | J29: 2324940
A30: Unavailable revenue - other | K30: 87390 | L30: 1188013.1
A31: Total deferred inflows of resources | B31: =B26+B27+B28+B29+B30 -> 78926304 | C31: =C26+C27+C28+C29+C30 -> 84487772 | D31: =D26+D27+D28+D29+D30 -> 88016669 | E31: =E26+E27+E28+E29+E30 -> 99840309 | F31: =F26+F27+F28+F29+F30 -> 102642085 | G31: =G26+G27+G28+G29+G30 -> 109319621 | H31: =H26+H27+H28+H29+H30 -> 113081244 | I31: =I26+I27+I28+I29+I30 -> 115741444 | ... L31: =L26+L27+L28+L29+L30 -> 1.3132041e+08
A32: FUND BALANCES
A33: Nonspendable | B33: 1097341 | C33: 1128938 | D33: 1519927 | E33: 1533248 | F33: 1567063 | G33: 1650060 | H33: 1662712 | I33: 1870633 | J33: 1872795 | K33: 254296 | L33: 1337599.6
A34: Restricted | B34: 19717565 | C34: 38154653 | D34: 16743861 | E34: 67061809 | F34: 71072315 | G34: 74122484 | H34: 30292753 | I34: 25141656 | J34: 102891288 | K34: 34636905 | L34: 29053748
A35: Committed
A36: Assigned
A37: Unassigned | B37: 11544614 | C37: 15339260 | D37: 18550551 | E37: 17237568 | F37: 11270502 | G37: 6876239 | H37: 11653470 | I37: 5356550 | J37: 4960343 | K37: 15298475 | L37: 11300062
A38: Total fund balances | B38: =B33+B34+B35+B36+B37 -> 32359520 | C38: =C33+C34+C35+C36+C37 -> 54622851 | D38: =D33+D34+D35+D36+D37 -> 36814339 | E38: =E33+E34+E35+E36+E37 -> 85832625 | F38: =F33+F34+F35+F36+F37 -> 83909880 | G38: =G33+G34+G35+G36+G37 -> 82648783 | H38: =H33+H34+H35+H36+H37 -> 43608935 | I38: =I33+I34+I35+I36+I37 -> 32368839 | ... L38: =L33+L34+L35+L36+L37 -> 41691410
A39: Total liabilities, deferred inflows and fund balances | B39: =B24+B31+B38 -> 134587758 | C39: =C24+C31+C38 -> 164635738 | D39: =D24+D31+D38 -> 148044626 | E39: =E24+E31+E38 -> 212621879 | F39: =F24+F31+F38 -> 218247861 | G39: =G24+G31+G38 -> 223184404 | H39: =H24+H31+H38 -> 184253386 | I39: =I24+I31+I38 -> 173998862 | ... L39: =L24+L31+L38 -> 2.078826e+08
A41: Balance check (Total assets − L − DI − FB) | B41: =B17-B39 -> 0 | C41: =C17-C39 -> 0 | D41: =D17-D39 -> 0 | E41: =E17-E39 -> 0 | F41: =F17-F39 -> 0 | G41: =G17-G39 -> 0 | H41: =H17-H39 -> 0 | I41: =I17-I39 -> 0 | ... L41: =L17-L39 -> 0
